cherab_inversion-0.3.1.dist-info/METADATA
cherab_inversion-0.3.1.dist-info/WHEEL
cherab_inversion-0.3.1.dist-info/LICENSE.md
cherab/inversion/version.py
cherab/inversion/__init__.py
cherab/inversion/derivative.py
cherab/inversion/core.py
cherab/inversion/gcv.py
cherab/inversion/lcurve.py
cherab/inversion/mfr.py
cherab/inversion/tools/__init__.py
cherab/inversion/tools/spinner.py
cherab/inversion/tools/scientific_format.py
cherab/inversion/tools/tests/__init__.py
cherab/inversion/tools/tests/test_spinner.py
cherab/inversion/tools/tests/test_scientific_format.py
cherab/inversion/data/__init__.py
cherab/inversion/data/bolo.npz
cherab/inversion/tests/__init__.py
cherab/inversion/tests/conftest.py
cherab/inversion/tests/test_core.py
cherab/inversion/tests/test_derivative.py
cherab/inversion/tests/test_gcv.py
cherab/inversion/tests/test_lcurve.py
cherab/inversion/tests/test_mfr.py
cherab_inversion-0.3.1.dist-info/RECORD
