Metadata-Version: 2.1
Name: cherab-inversion
Version: 0.3.1
Summary: Cherab inversion framework
Author-Email: Koyo Munechika <munechika.koyo@torus.nr.titech.ac.jp>
Maintainer-Email: Koyo Munechika <munechika.koyo@torus.nr.titech.ac.jp>
License: BSD 3-Clause License
Classifier: Development Status :: 5 - Production/Stable
Classifier: Intended Audience :: Science/Research
Classifier: Intended Audience :: Education
Classifier: Intended Audience :: Developers
Classifier: License :: OSI Approved :: BSD License
Classifier: Operating System :: POSIX :: Linux
Classifier: Operating System :: POSIX
Classifier: Operating System :: Unix
Classifier: Operating System :: MacOS
Classifier: Operating System :: Microsoft :: Windows
Classifier: Programming Language :: Python :: 3.9
Classifier: Programming Language :: Python :: 3.10
Classifier: Programming Language :: Python :: 3.11
Classifier: Programming Language :: Python :: 3.12
Classifier: Topic :: Scientific/Engineering :: Physics
Project-URL: Homepage, https://cherab-inversion.readthedocs.io/
Project-URL: Documentation, https://cherab-inversion.readthedocs.io/
Project-URL: Repository, https://github.com/munechika-koyo/cherab_inversion
Requires-Python: >=3.9
Requires-Dist: numpy
Requires-Dist: scipy
Requires-Dist: matplotlib
Requires-Dist: scikit-sparse
